gotailwind/__init__.py
gotailwind/cli/__init__.py
gotailwind/cli/async_typer.py
gotailwind/cli/ruff.toml
gotailwind/const.py
gotailwind/exceptions.py
gotailwind/models.py
gotailwind/py.typed
gotailwind/tailwind.py
gotailwind/util.py
gotailwind-0.3.0.dist-info/LICENSE.md
gotailwind-0.3.0.dist-info/METADATA
gotailwind-0.3.0.dist-info/WHEEL
gotailwind-0.3.0.dist-info/entry_points.txt
gotailwind-0.3.0.dist-info/RECORD
