Metadata-Version: 2.1
Name: gotailwind
Version: 0.3.0
Summary: Asynchronous Python client for Tailwind garage door openers.
Home-page: https://github.com/frenck/python-gotailwind
License: MIT
Keywords: gotailwind,tailwind,iq3,myq,chamberlain,craftsman,liftmaster
Author: Franck Nijhof
Author-email: opensource@frenck.dev
Maintainer: Franck Nijhof
Maintainer-email: opensource@frenck.dev
Requires-Python: >=3.11,<4.0
Classifier: Development Status :: 5 - Production/Stable
Classifier: Framework :: AsyncIO
Classifier: Intended Audience :: Developers
Classifier: License :: OSI Approved :: MIT License
Classifier: Natural Language :: English
Classifier: Programming Language :: Python :: 3
Classifier: Programming Language :: Python :: 3.11
Classifier: Programming Language :: Python :: 3.12
Classifier: Programming Language :: Python :: 3.13
Classifier: Topic :: Software Development :: Libraries :: Python Modules
Provides-Extra: cli
Requires-Dist: aiohttp (>=3.0.0)
Requires-Dist: awesomeversion (>=22.8.0)
Requires-Dist: backoff (>=2.2.1)
Requires-Dist: mashumaro (>=3.10)
Requires-Dist: orjson (>=3.9.8)
Requires-Dist: typer[all] (>=0.9) ; extra == "cli"
Requires-Dist: yarl (>=1.6.0)
Requires-Dist: zeroconf (>=0.126.0)
Project-URL: Bug Tracker, https://github.com/frenck/python-gotailwind/issues
Project-URL: Changelog, https://github.com/frenck/python-gotailwind/releases
Project-URL: Documentation, https://github.com/frenck/python-gotailwind
Project-URL: Repository, https://github.com/frenck/python-gotailwind
